einspect/__init__.py
einspect/_compat/__init__.py
einspect/_compat/py_function_3_10.py
einspect/_compat/py_function_3_9.py
einspect/_compat/py_unicode_3_12.py
einspect/_patch.py
einspect/_typing.py
einspect/api.py
einspect/compat.py
einspect/errors.py
einspect/protocols/__init__.py
einspect/protocols/delayed_bind.py
einspect/protocols/type_parse.py
einspect/py.typed
einspect/structs/__init__.py
einspect/structs/deco.py
einspect/structs/include/__init__.py
einspect/structs/include/descrobject_h.py
einspect/structs/include/methodobject_h.py
einspect/structs/include/object_h.py
einspect/structs/include/pybuffer_h.py
einspect/structs/mapping_proxy.py
einspect/structs/py_bool.py
einspect/structs/py_cfunction.py
einspect/structs/py_dict.py
einspect/structs/py_float.py
einspect/structs/py_function.py
einspect/structs/py_gc.py
einspect/structs/py_list.py
einspect/structs/py_long.py
einspect/structs/py_object.py
einspect/structs/py_set.py
einspect/structs/py_tuple.py
einspect/structs/py_type.py
einspect/structs/py_unicode.py
einspect/structs/slots_map.py
einspect/structs/traits.py
einspect/type_orig.py
einspect/types.py
einspect/views/__init__.py
einspect/views/_display.py
einspect/views/_moves.py
einspect/views/factory.py
einspect/views/unsafe.py
einspect/views/view_base.py
einspect/views/view_bool.py
einspect/views/view_cfunction.py
einspect/views/view_dict.py
einspect/views/view_float.py
einspect/views/view_function.py
einspect/views/view_int.py
einspect/views/view_list.py
einspect/views/view_mapping_proxy.py
einspect/views/view_set.py
einspect/views/view_str.py
einspect/views/view_tuple.py
einspect/views/view_type.py
einspect-0.5.16.dist-info/LICENSE
einspect-0.5.16.dist-info/WHEEL
einspect-0.5.16.dist-info/METADATA
einspect-0.5.16.dist-info/RECORD
