Metadata-Version: 2.1
Name: einspect
Version: 0.5.16
Summary: Extended Inspect - view and modify memory structs of runtime objects.
Home-page: https://github.com/ionite34/einspect
License: MIT
Keywords: einspect,inspect,inspections,extensions,inspect-extensions,ctypes,ctypes-extensions,pointers,structs,memory,mutate,setattr,modify
Author: ionite34
Author-email: dev@ionite.io
Requires-Python: >=3.8,<3.13
Classifier: License :: OSI Approved :: MIT License
Classifier: Operating System :: OS Independent
Classifier: Programming Language :: Python :: 3
Classifier: Programming Language :: Python :: 3.8
Classifier: Programming Language :: Python :: 3.9
Classifier: Programming Language :: Python :: 3.10
Classifier: Programming Language :: Python :: 3.11
Classifier: Programming Language :: Python :: 3.11
Classifier: Programming Language :: Python :: 3.12
Classifier: Programming Language :: Python :: Implementation :: CPython
Classifier: Topic :: Software Development :: Debuggers
Classifier: Topic :: Software Development :: Libraries
Classifier: Topic :: Software Development :: Libraries :: Python Modules
Classifier: Typing :: Typed
Requires-Dist: typing-extensions (>=4.4.0,<5.0.0)
Project-URL: Documentation, https://docs.ionite.io/einspect
Project-URL: Repository, https://github.com/ionite34/einspect
